[
  {
    "trainNo": "ACE01",
    "returningTrainNo": "",
    "loco1": "",
    "loco2": "",
    "car1": "",
    "car2": "",
    "car3": "",
    "car4": "",
    "car5": "",
    "car6": "",
    "car7": "",
    "car8": ""
  },
  {
    "trainNo": "ACE21",
    "returningTrainNo": "",
    "loco1": "1234",
    "loco2": "1234",
    "car1": "123",
    "car2": "",
    "car3": "",
    "car4": "123456",
    "car5": "",
    "car6": "",
    "car7": "",
    "car8": ""
  },
  {
    "trainNo": "ACE33",
    "returningTrainNo": "",
    "loco1": "",
    "loco2": "",
    "car1": "",
    "car2": "1111",
    "car3": "",
    "car4": "",
    "car5": "",
    "car6": "",
    "car7": "",
    "car8": ""
  },
  {
    "from_date": "2023-08-29",
    "to_date": "2023-09-04"
  }
]